Workbook

Sheet Export Summary
B3: This document was exported from Numbers. Each table was converted to an Excel worksheet. All other objects on each Numbers sheet were placed on separate worksheets. Please be aware that formula calculations may differ in Excel.
B7: Numbers Sheet Name | C7: Numbers Table Name | D7: Excel Worksheet Name
B9: Withdrawal - Card Matrix
C10: Table 1 | D10: Withdrawal - Card Matrix
B11: Withdrawal - Card Matrix
C12: Table 1 | D12: Withdrawal - Card Matrix
B13: Withdrawal Summary
C14: Table 1 | D14: Withdrawal Summary
B15: Execution Report
C16: Table 1 | D16: Execution Report
B17: Summary
C18: Table 1 | D18: Summary

Sheet Withdrawal - Card Matrix
A1: CRM PRE-PROD – WITHDRAWAL COMPLETION REPORT | VISA / MASTERCARD / JCB
A2: Environment | B2: Hitachi CRM – Pre-Prod
A3: Transaction Type | B3: Cash Withdrawal
A4: Execution Date | B4: 24/09/2026
A5: Tester | B5: Team Channel
A6: Scope | B6: Visa, Mastercard and JCB card-based withdrawal transactions
A8: TC ID | B8: Card Scheme | C8: Card Type | D8: Issuing Bank | E8: Account Type | F8: Withdrawal Amount | G8: ATM / CRM ID | H8: Account / Reference No. | I8: RRN | J8: STAN / UTANO | K8: FE Status | L8: SIBS / CBS Status | M8: Receipt / Output | N8: Overall Status | O8: Execution Date | P8: Tester | Q8: Remarks
A9: WD-001 | B9: Visa | C9: Debit | D9: People's Bank | E9: CHK
A10: WD-002 | B10: Visa | C10: Debit | D10: People's Bank | E10: SA
A11: WD-003 | B11: Mastercard | C11: Debit | D11: People's Bank | E11: CHK
A12: WD-004 | B12: Mastercard | C12: Debit | D12: People's Bank | E12: SA
A13: WD-005 | B13: JCB | C13: Debit | D13: People's Bank | E13: CHK
A14: WD-006 | B14: JCB | C14: Debit | D14: People's Bank | E14: SA
A15: WD-007 | B15: Visa | C15: Credit | D15: People's Bank | E15: Credit Card
A16: WD-004 | B16: Visa | C16: Debit | D16: Other Bank | E16: Other Bank Account
A17: WD-005 | B17: Visa | C17: Credit | D17: Other Bank | E17: Other Bank Credit
A18: WD-006 | B18: Mastercard | C18: Debit | D18: People's Bank | E18: CHK
A19: WD-007 | B19: Mastercard | C19: Debit | D19: People's Bank | E19: SA
A20: WD-008 | B20: Mastercard | C20: Debit | D20: People's Bank | E20: BGP
... A30: WD-018 | B30: JCB | C30: Credit | D30: Other Bank | E30: Other Bank Credit

Sheet Withdrawal Summary
A1: WITHDRAWAL – VISA / MASTERCARD / JCB SUMMARY
A3: Card Scheme | B3: Total | C3: Passed | D3: Failed | E3: Blocked | F3: Not Executed
A4: Visa | B4: {=COUNTIF('Withdrawal Summary'!B9:B61,A4)} -> 5 | C4: {=_xlfn.COUNTIFS('Withdrawal Summary'!B9:B61,A4,'Withdrawal Summary'!N9:N61,"PASS")} -> 0 | D4: {=_xlfn.COUNTIFS('Withdrawal Summary'!B9:B61,A4,'Withdrawal Summary'!N9:N61,"FAIL")} -> 0 | E4: {=_xlfn.COUNTIFS('Withdrawal Summary'!B9:B61,A4,'Withdrawal Summary'!N9:N61,"BLOCKED")} -> 0 | F4: {=_xlfn.COUNTIFS('Withdrawal Summary'!B9:B61,A4,'Withdrawal Summary'!N9:N61,"NOT EXECUTED")} -> 0
A5: Mastercard | B5: {=COUNTIF('Withdrawal Summary'!B9:B61,A5)} -> 9 | C5: {=_xlfn.COUNTIFS('Withdrawal Summary'!B9:B61,A5,'Withdrawal Summary'!N9:N61,"PASS")} -> 0 | D5: {=_xlfn.COUNTIFS('Withdrawal Summary'!B9:B61,A5,'Withdrawal Summary'!N9:N61,"FAIL")} -> 0 | E5: {=_xlfn.COUNTIFS('Withdrawal Summary'!B9:B61,A5,'Withdrawal Summary'!N9:N61,"BLOCKED")} -> 0 | F5: {=_xlfn.COUNTIFS('Withdrawal Summary'!B9:B61,A5,'Withdrawal Summary'!N9:N61,"NOT EXECUTED")} -> 0
A6: JCB | B6: {=COUNTIF('Withdrawal Summary'!B9:B61,A6)} -> 8 | C6: {=_xlfn.COUNTIFS('Withdrawal Summary'!B9:B61,A6,'Withdrawal Summary'!N9:N61,"PASS")} -> 0 | D6: {=_xlfn.COUNTIFS('Withdrawal Summary'!B9:B61,A6,'Withdrawal Summary'!N9:N61,"FAIL")} -> 0 | E6: {=_xlfn.COUNTIFS('Withdrawal Summary'!B9:B61,A6,'Withdrawal Summary'!N9:N61,"BLOCKED")} -> 0 | F6: {=_xlfn.COUNTIFS('Withdrawal Summary'!B9:B61,A6,'Withdrawal Summary'!N9:N61,"NOT EXECUTED")} -> 0
A8: Overall Withdrawal Completion | B8: {=IF(COUNTA('Withdrawal Summary'!A9:A61)=0,0,COUNTIF('Withdrawal Summary'!N9:N61,"PASS")/COUNTA('Withdrawal Summary'!A9:A61))} -> 0
A9: Overall Pass Rate | B9: {=IF((COUNTIF('Withdrawal Summary'!N9:N61,"PASS")+COUNTIF('Withdrawal Summary'!N9:N61,"FAIL"))=0,0,COUNTIF('Withdrawal Summary'!N9:N61,"PASS")/(COUNTIF('Withdrawal Summary'!N9:N61,"PASS")+COUNTIF('Withdrawal Summary'!N9:N61,"FAIL")))} -> 0

Sheet Execution Report
A1: CRM PRE-PROD – ALL TRANSACTIONS COMPLETION REPORT
A2: Environment | B2: Hitachi CRM – Pre-Prod
A3: Execution Date | B3: 24/09/2026
A4: Tester | B4: Team Channel
A5: UAT Scope | B5: All applicable card-based and cardless CRM transactions
A7: TC ID | B7: Transaction Category | C7: Transaction / Test Description | D7: Card Type | E7: Account / Reference No. | F7: Amount | G7: RRN | H7: STAN / UTANO | I7: Before Balance | J7: After Balance | K7: FE Status | L7: Switch Status | M7: SIBS / CBS Status | N7: Receipt / Output | O7: Overall Status | P7: Execution Date | Q7: Tester | R7: Remarks
A8: CB_DEP_001 | B8: Deposit | C8: Cash Deposit – People’s Bank Account(CHK) | D8: Visa
A9: CB_DEP_002 | B9: Deposit | C9: Cash Deposit - People's Bank Account(SA) | D9: Visa
A10: CB_DEP_003 | B10: Deposit | C10: Cash Deposit - People's Bank Account(SA) | D10: Mastercard
A11: CB_DEP_004 | B11: Deposit | C11: Cash Deposit – People’s Bank Account(CHK) | D11: Mastercard
A12: CB_DEP_005 | B12: Deposit | C12: Cash Deposit - People's Bank Account(SA) | D12: JCB
A13: CB_DEP_006 | B13: Deposit | C13: Cash Deposit – People’s Bank Account(CHK) | D13: JCB
A14: CB_FT_001 | B14: Fund Transfer | C14: Fund Transfer – SA to CHK | D14: Visa
A15: CB_FT_002 | B15: Fund Transfer | C15: Fund Transfer – CHE to SA | D15: Visa
A16: CB_FT_003 | B16: Fund Transfer | C16: Fund Transfer – CHE to SA | D16: Mastercard
A17: CB_FT_004 | B17: Fund Transfer | C17: Fund Transfer – SA to CHK | D17: Mastercard
A18: CB_FT_005 | B18: Fund Transfer | C18: Fund Transfer – CHE to SA | D18: JCB
A19: CB_FT_006 | B19: Fund Transfer | C19: Fund Transfer – SA to CHK | D19: JCB
... A87: CL_BP_013 | B87: Cardless Transaction | C87: Cardless Bill Payment - PLC | D87: Cardless

Sheet Summary
A1: CRM PRE-PROD – UAT EXECUTION SUMMARY
A3: Environment | B3: {='Summary'!B2} -> Hitachi CRM – Pre-Prod
A4: Execution Date | B4: {='Summary'!B3} -> 24/09/2026
A5: Tester | B5: {='Summary'!B4} -> Team Channel
A6: Total Test Cases | B6: {=COUNTA('Summary'!A8:A87)} -> 76
A7: Passed | B7: {=COUNTIF('Summary'!O8:O87,"PASS")} -> 0
A8: Failed | B8: {=COUNTIF('Summary'!O8:O87,"FAIL")} -> 0
A9: Blocked | B9: {=COUNTIF('Summary'!O8:O87,"BLOCKED")} -> 0
A10: Not Executed | B10: {=COUNTIF('Summary'!O8:O87,"NOT EXECUTED")} -> 0
A11: Pending | B11: {=COUNTIF('Summary'!O8:O87,"PENDING")} -> 0
A12: Completion % | B12: {=IF(B4=0,0,(B5+B6+B7+B8)/B4)}
A13: Pass Rate % | B13: {=IF((B5+B6)=0,0,B5/(B5+B6))}
A16: Transaction Category Summary
A17: Category | B17: Total | C17: Passed | D17: Failed | E17: Blocked | F17: Not Executed
A18: Withdrawal | B18: {=COUNTIF('Summary'!B8:B87,A18)} -> 0 | C18: {=_xlfn.COUNTIFS('Summary'!B8:B87,A18,'Summary'!O8:O87,"PASS")} -> 0 | D18: {=_xlfn.COUNTIFS('Summary'!B8:B87,A18,'Summary'!O8:O87,"FAIL")} -> 0 | E18: {=_xlfn.COUNTIFS('Summary'!B8:B87,A18,'Summary'!O8:O87,"BLOCKED")} -> 0 | F18: {=_xlfn.COUNTIFS('Summary'!B8:B87,A18,'Summary'!O8:O87,"NOT EXECUTED")} -> 0
A19: Deposit | B19: {=COUNTIF('Summary'!B8:B87,A19)} -> 6 | C19: {=_xlfn.COUNTIFS('Summary'!B8:B87,A19,'Summary'!O8:O87,"PASS")} -> 0 | D19: {=_xlfn.COUNTIFS('Summary'!B8:B87,A19,'Summary'!O8:O87,"FAIL")} -> 0 | E19: {=_xlfn.COUNTIFS('Summary'!B8:B87,A19,'Summary'!O8:O87,"BLOCKED")} -> 0 | F19: {=_xlfn.COUNTIFS('Summary'!B8:B87,A19,'Summary'!O8:O87,"NOT EXECUTED")} -> 0
A20: Fund Transfer | B20: {=COUNTIF('Summary'!B8:B87,A20)} -> 6 | C20: {=_xlfn.COUNTIFS('Summary'!B8:B87,A20,'Summary'!O8:O87,"PASS")} -> 0 | D20: {=_xlfn.COUNTIFS('Summary'!B8:B87,A20,'Summary'!O8:O87,"FAIL")} -> 0 | E20: {=_xlfn.COUNTIFS('Summary'!B8:B87,A20,'Summary'!O8:O87,"BLOCKED")} -> 0 | F20: {=_xlfn.COUNTIFS('Summary'!B8:B87,A20,'Summary'!O8:O87,"NOT EXECUTED")} -> 0
A21: Balance Inquiry | B21: {=COUNTIF('Summary'!B8:B87,A21)} -> 6 | C21: {=_xlfn.COUNTIFS('Summary'!B8:B87,A21,'Summary'!O8:O87,"PASS")} -> 0 | D21: {=_xlfn.COUNTIFS('Summary'!B8:B87,A21,'Summary'!O8:O87,"FAIL")} -> 0 | E21: {=_xlfn.COUNTIFS('Summary'!B8:B87,A21,'Summary'!O8:O87,"BLOCKED")} -> 0 | F21: {=_xlfn.COUNTIFS('Summary'!B8:B87,A21,'Summary'!O8:O87,"NOT EXECUTED")} -> 0
A22: Mini Statement | B22: {=COUNTIF('Summary'!B8:B87,A22)} -> 9 | C22: {=_xlfn.COUNTIFS('Summary'!B8:B87,A22,'Summary'!O8:O87,"PASS")} -> 0 | D22: {=_xlfn.COUNTIFS('Summary'!B8:B87,A22,'Summary'!O8:O87,"FAIL")} -> 0 | E22: {=_xlfn.COUNTIFS('Summary'!B8:B87,A22,'Summary'!O8:O87,"BLOCKED")} -> 0 | F22: {=_xlfn.COUNTIFS('Summary'!B8:B87,A22,'Summary'!O8:O87,"NOT EXECUTED")} -> 0
A23: PIN Change | B23: {=COUNTIF('Summary'!B8:B87,A23)} -> 3 | C23: {=_xlfn.COUNTIFS('Summary'!B8:B87,A23,'Summary'!O8:O87,"PASS")} -> 0 | D23: {=_xlfn.COUNTIFS('Summary'!B8:B87,A23,'Summary'!O8:O87,"FAIL")} -> 0 | E23: {=_xlfn.COUNTIFS('Summary'!B8:B87,A23,'Summary'!O8:O87,"BLOCKED")} -> 0 | F23: {=_xlfn.COUNTIFS('Summary'!B8:B87,A23,'Summary'!O8:O87,"NOT EXECUTED")} -> 0
A24: Bill Payment | B24: {=COUNTIF('Summary'!B8:B87,A24)} -> 33 | C24: {=_xlfn.COUNTIFS('Summary'!B8:B87,A24,'Summary'!O8:O87,"PASS")} -> 0 | D24: {=_xlfn.COUNTIFS('Summary'!B8:B87,A24,'Summary'!O8:O87,"FAIL")} -> 0 | E24: {=_xlfn.COUNTIFS('Summary'!B8:B87,A24,'Summary'!O8:O87,"BLOCKED")} -> 0 | F24: {=_xlfn.COUNTIFS('Summary'!B8:B87,A24,'Summary'!O8:O87,"NOT EXECUTED")} -> 0
A25: Cardless Transaction | B25: {=COUNTIF('Summary'!B8:B87,A25)} -> 13 | C25: {=_xlfn.COUNTIFS('Summary'!B8:B87,A25,'Summary'!O8:O87,"PASS")} -> 0 | D25: {=_xlfn.COUNTIFS('Summary'!B8:B87,A25,'Summary'!O8:O87,"FAIL")} -> 0 | E25: {=_xlfn.COUNTIFS('Summary'!B8:B87,A25,'Summary'!O8:O87,"BLOCKED")} -> 0 | F25: {=_xlfn.COUNTIFS('Summary'!B8:B87,A25,'Summary'!O8:O87,"NOT EXECUTED")} -> 0
